mash_client/__init__.py
mash_client/cli_utils.py
mash_client/controller.py
mash_client/mash_client_exceptions.py
mash_client/cli/__init__.py
mash_client/cli/config.py
mash_client/cli/user.py
mash_client/cli/account/__init__.py
mash_client/cli/account/aliyun.py
mash_client/cli/account/azure.py
mash_client/cli/account/ec2.py
mash_client/cli/account/gce.py
mash_client/cli/account/oci.py
mash_client/cli/auth/__init__.py
mash_client/cli/auth/token.py
mash_client/cli/job/__init__.py
mash_client/cli/job/aliyun.py
mash_client/cli/job/azure.py
mash_client/cli/job/ec2.py
mash_client/cli/job/gce.py
mash_client/cli/job/oci.py
mash_client-4.6.0.dist-info/licenses/LICENSE
mash_client-4.6.0.dist-info/METADATA
mash_client-4.6.0.dist-info/WHEEL
mash_client-4.6.0.dist-info/entry_points.txt
mash_client-4.6.0.dist-info/top_level.txt
mash_client-4.6.0.dist-info/RECORD
