Metadata-Version: 2.4
Name: mash-client
Version: 4.6.0
Summary: CLI client for interfacing with a MASH server.
Home-page: https://github.com/SUSE-enceladus/mash-client
Author: SUSE
Author-email: public-cloud-dev@susecloud.net
License: GPLv3+
Keywords: mash-client mash client
Classifier: Development Status :: 3 - Alpha
Classifier: Environment :: Console
Classifier: Intended Audience :: Developers
Classifier: Topic :: Utilities
Classifier: License :: OSI Approved :: GNU General Public License v3 or later (GPLv3+)
Classifier: Natural Language :: English
Classifier: Programming Language :: Python :: 3
Classifier: Programming Language :: Python :: 3.8
Classifier: Programming Language :: Python :: 3.9
Classifier: Programming Language :: Python :: 3.10
Classifier: Programming Language :: Python :: 3.11
Classifier: Programming Language :: Python :: 3.12
Requires-Python: >=3.8
License-File: LICENSE
Requires-Dist: Click
Requires-Dist: requests
Requires-Dist: PyYAML
Requires-Dist: PyJWT
Provides-Extra: dev
Requires-Dist: Click; extra == "dev"
Requires-Dist: requests; extra == "dev"
Requires-Dist: PyYAML; extra == "dev"
Requires-Dist: PyJWT; extra == "dev"
Requires-Dist: bumpversion; extra == "dev"
Requires-Dist: coverage; extra == "dev"
Requires-Dist: pytest; extra == "dev"
Requires-Dist: pytest-cov; extra == "dev"
Requires-Dist: flake8; extra == "dev"
Requires-Dist: Sphinx; extra == "dev"
Requires-Dist: sphinx-click; extra == "dev"
Dynamic: author
Dynamic: author-email
Dynamic: classifier
Dynamic: description
Dynamic: description-content-type
Dynamic: home-page
Dynamic: keywords
Dynamic: license
Dynamic: license-file
Dynamic: provides-extra
Dynamic: requires-dist
Dynamic: requires-python
Dynamic: summary
